lfp/__init__.py
lfp/__main__.py
lfp/choices.py
lfp/main.py
lfp/new.py
lfp/py.typed
lfp/parsers/api.py
lfp/parsers/cst.py
lfp-0.5.1.dist-info/METADATA
lfp-0.5.1.dist-info/WHEEL
lfp-0.5.1.dist-info/entry_points.txt
lfp-0.5.1.dist-info/licenses/LICENSE
lfp-0.5.1.dist-info/RECORD
