Metadata-Version: 2.4
Name: lfp
Version: 0.5.1
Summary: Battery pack for your Django project
Author-email: Sarthak Jariwala <sarthak@sarthakjariwala.com>
License-File: LICENSE
Requires-Python: >=3.9
Requires-Dist: copier>=9.4.1
Requires-Dist: libcst>=1.6.0
Requires-Dist: questionary>=2.1.0
Requires-Dist: typer>=0.15.1
